libvpet/__init__.py
libvpet/libvpet.py
libvpet-0.2.0.dist-info/METADATA
libvpet-0.2.0.dist-info/WHEEL
libvpet-0.2.0.dist-info/top_level.txt
libvpet-0.2.0.dist-info/RECORD
