Metadata-Version: 2.1
Name: libvpet
Version: 0.2.0
Summary: A virtual pet library for Python
Author-email: sctech <gamerselimiko@gmail.com>
License: MIT
Project-URL: Source, https://github.com/sctech-tr/libvpet
Keywords: virtual pet,game,library,python
Classifier: Programming Language :: Python :: 3
Classifier: License :: OSI Approved :: MIT License
Classifier: Operating System :: OS Independent
